gocept.collmex-2.1.0-py3.11-nspkg.pth
gocept/collmex/__init__.py
gocept/collmex/collmex.py
gocept/collmex/doctest.rst
gocept/collmex/interfaces.py
gocept/collmex/model.py
gocept/collmex/testing.py
gocept/collmex/utils.py
gocept/collmex/tests/__init__.py
gocept/collmex/tests/test_collmex.py
gocept/collmex/tests/test_model.py
gocept/collmex/tests/test_testing.py
gocept/collmex/tests/test_thread.py
gocept.collmex-2.1.0.dist-info/METADATA
gocept.collmex-2.1.0.dist-info/WHEEL
gocept.collmex-2.1.0.dist-info/namespace_packages.txt
gocept.collmex-2.1.0.dist-info/top_level.txt
gocept.collmex-2.1.0.dist-info/RECORD
