Metadata-Version: 2.1
Name: gocept.collmex
Version: 2.1.0
Summary: Python-bindings for the Collmex import/export API
Home-page: https://github.com/gocept/gocept.collmex
Author: gocept
Author-email: mail@gocept.com
License: ZPL 2.1
Classifier: Development Status :: 5 - Production/Stable
Classifier: Environment :: Plugins
Classifier: Intended Audience :: Developers
Classifier: License :: OSI Approved
Classifier: License :: OSI Approved :: Zope Public License
Classifier: Operating System :: OS Independent
Classifier: Programming Language :: Python :: 3
Classifier: Programming Language :: Python :: 3.7
Classifier: Programming Language :: Python :: 3.8
Classifier: Programming Language :: Python :: 3.9
Classifier: Programming Language :: Python :: 3.10
Classifier: Programming Language :: Python :: 3.11
Classifier: Programming Language :: Python :: Implementation :: CPython
Classifier: Programming Language :: Python :: Implementation :: PyPy
Requires-Python: >=3.7
Requires-Dist: gocept.cache >=0.6.1
Requires-Dist: setuptools >=1.0
Requires-Dist: transaction >=1.4
Requires-Dist: zope.deprecation >=4.0
Requires-Dist: zope.interface >=4.0
Requires-Dist: webtest >=2.0
Requires-Dist: wsgiproxy2
Provides-Extra: test
Requires-Dist: zope.testing >=4.0 ; extra == 'test'
Requires-Dist: mock >=1.0 ; extra == 'test'
